Metadata-Version: 2.1
Name: popsynth
Version: 1.1.1
Summary: A population synthesis code
Home-page: https://github.com/grburgess/popsynth
Author: J. Michael Burgess
Author-email: jmichaelburgess@gmail.com
License: GPL-3+
Project-URL: Bug Tracker, https://github.com/grburgess/popsynth/issues
Project-URL: Source Code, https://github.com/grburgess/popsynth
Classifier: Development Status :: 5 - Production/Stable
Classifier: Environment :: Console
Classifier: Intended Audience :: Science/Research
Classifier: License :: OSI Approved :: GNU General Public License v3 or later (GPLv3+)
Classifier: Operating System :: POSIX
Classifier: Programming Language :: Python :: 3.7
Classifier: Programming Language :: Python :: 3.8
Classifier: Programming Language :: Python :: 3.9
Classifier: Topic :: Scientific/Engineering :: Physics
License-File: LICENSE
Requires-Dist: numpy
Requires-Dist: scipy
Requires-Dist: ipython
Requires-Dist: matplotlib
Requires-Dist: astropy
Requires-Dist: h5py
Requires-Dist: ipyvolume (>=0.6.0a2)
Requires-Dist: pythreejs
Requires-Dist: cython
Requires-Dist: betagen
Requires-Dist: tqdm
Requires-Dist: numba
Requires-Dist: pandas
Requires-Dist: networkx
Requires-Dist: dotmap
Requires-Dist: omegaconf
Requires-Dist: colorama
Requires-Dist: class-registry
